replay_trajectory_classification/__init__.py
replay_trajectory_classification/classifier.py
replay_trajectory_classification/clusterless_simulation.py
replay_trajectory_classification/continuous_state_transitions.py
replay_trajectory_classification/core.py
replay_trajectory_classification/decoder.py
replay_trajectory_classification/discrete_state_transitions.py
replay_trajectory_classification/environments.py
replay_trajectory_classification/initial_conditions.py
replay_trajectory_classification/observation_model.py
replay_trajectory_classification/simulate.py
replay_trajectory_classification/sorted_spikes_simulation.py
replay_trajectory_classification/standard_decoder.py
replay_trajectory_classification/likelihoods/__init__.py
replay_trajectory_classification/likelihoods/calcium_likelihood.py
replay_trajectory_classification/likelihoods/diffusion.py
replay_trajectory_classification/likelihoods/multiunit_likelihood.py
replay_trajectory_classification/likelihoods/multiunit_likelihood_gpu.py
replay_trajectory_classification/likelihoods/multiunit_likelihood_integer.py
replay_trajectory_classification/likelihoods/multiunit_likelihood_integer_gpu.py
replay_trajectory_classification/likelihoods/multiunit_likelihood_integer_gpu_log.py
replay_trajectory_classification/likelihoods/multiunit_likelihood_track_graph.py
replay_trajectory_classification/likelihoods/spiking_likelihood_glm.py
replay_trajectory_classification/likelihoods/spiking_likelihood_kde.py
replay_trajectory_classification/likelihoods/spiking_likelihood_kde_gpu.py
replay_trajectory_classification-1.4.1.dist-info/LICENSE
replay_trajectory_classification-1.4.1.dist-info/METADATA
replay_trajectory_classification-1.4.1.dist-info/WHEEL
replay_trajectory_classification-1.4.1.dist-info/top_level.txt
replay_trajectory_classification-1.4.1.dist-info/RECORD
