Metadata-Version: 2.1
Name: replay_trajectory_classification
Version: 1.4.1
Summary: Classify replay trajectories.
Home-page: https://github.com/Eden-Kramer-Lab/replay_trajectory_classification
Author: Eric Denovellis
Author-email: eric.denovellis@ucsf.edu
License: MIT
License-File: LICENSE
Requires-Dist: numpy
Requires-Dist: statsmodels
Requires-Dist: numba
Requires-Dist: matplotlib
Requires-Dist: pandas
Requires-Dist: xarray
Requires-Dist: scipy
Requires-Dist: scikit-learn
Requires-Dist: scikit-image
Requires-Dist: regularized-glm
Requires-Dist: dask
Requires-Dist: distributed
Requires-Dist: patsy
Requires-Dist: networkx
Requires-Dist: joblib
Requires-Dist: track-linearization>=2.3.1
Requires-Dist: tqdm
Requires-Dist: seaborn
